LICENSE
README.md
setup.py
dgus/__init__.py
dgus/components/__init__.py
dgus/components/datavariablesdisplay.py
dgus/components/qrcode.py
dgus/components/returnkeycode.py
dgus/components/textdisplay.py
dgus/types/__init__.py
dgus/types/int.py
dgus/types/string.py
dgus/types/word.py
micropython_dgus.egg-info/PKG-INFO
micropython_dgus.egg-info/SOURCES.txt
micropython_dgus.egg-info/dependency_links.txt
micropython_dgus.egg-info/top_level.txt